django_user_activation/__init__.py
django_user_activation/activate.py
django_user_activation/apps.py
django_user_activation/tasks.py
django_user_activation/urls.py
django_user_activation/utils.py
django_user_activation/views.py
django_user_activation/templates/user_activation.html
django_user_activation/templates/user_activation.txt
django_user_activation-1.0.0.dist-info/LICENSE
django_user_activation-1.0.0.dist-info/METADATA
django_user_activation-1.0.0.dist-info/WHEEL
django_user_activation-1.0.0.dist-info/top_level.txt
django_user_activation-1.0.0.dist-info/RECORD
