Metadata-Version: 2.1
Name: django-user-activation
Version: 1.0.0
Summary: django-user-activation is a Django app to manage user activation on registration.
Author-email: Amr Elwetaidy <amr.elwetaidy@gmail.com>
Project-URL: Changelog, https://github.com/Amr-elwetaidy/django-user-activation/blob/main/CHANGELOG.rst
Project-URL: Repository, https://github.com/Amr-elwetaidy/django-user-activation
Keywords: django,user,activation
Classifier: Development Status :: 5 - Production/Stable
Classifier: Environment :: Web Environment
Classifier: Framework :: Django
Classifier: Framework :: Django :: 5.0
Classifier: Framework :: Django :: 5.1
Classifier: Intended Audience :: Developers
Classifier: License :: OSI Approved :: MIT License
Classifier: Natural Language :: English
Classifier: Operating System :: OS Independent
Classifier: Programming Language :: Python :: 3 :: Only
Classifier: Programming Language :: Python :: 3.10
Classifier: Programming Language :: Python :: 3.11
Classifier: Programming Language :: Python :: 3.12
Classifier: Programming Language :: Python :: 3.13
Classifier: Programming Language :: Python :: Implementation :: CPython
Classifier: Typing :: Typed
Requires-Python: >=3.10
License-File: LICENSE
Requires-Dist: django>=5.0
Requires-Dist: PyJWT>=2.9.0
